odoo/addons/ssi_warehouse_transfer/README.rst
odoo/addons/ssi_warehouse_transfer/__init__.py
odoo/addons/ssi_warehouse_transfer/__manifest__.py
odoo/addons/ssi_warehouse_transfer/menu.xml
odoo/addons/ssi_warehouse_transfer/data/approval_template_data.xml
odoo/addons/ssi_warehouse_transfer/data/base_automation_data.xml
odoo/addons/ssi_warehouse_transfer/data/ir_actions_server_data.xml
odoo/addons/ssi_warehouse_transfer/data/ir_sequence_data.xml
odoo/addons/ssi_warehouse_transfer/data/policy_template_data.xml
odoo/addons/ssi_warehouse_transfer/data/sequence_template_data.xml
odoo/addons/ssi_warehouse_transfer/i18n/ssi_warehouse_transfer.pot
odoo/addons/ssi_warehouse_transfer/models/__init__.py
odoo/addons/ssi_warehouse_transfer/models/stock_move.py
odoo/addons/ssi_warehouse_transfer/models/stock_rule.py
odoo/addons/ssi_warehouse_transfer/models/warehouse_transfer.py
odoo/addons/ssi_warehouse_transfer/models/warehouse_transfer_line.py
odoo/addons/ssi_warehouse_transfer/models/warehouse_transfer_type.py
odoo/addons/ssi_warehouse_transfer/security/ir.model.access.csv
odoo/addons/ssi_warehouse_transfer/security/ir_module_category_data.xml
odoo/addons/ssi_warehouse_transfer/security/ir_rule_data.xml
odoo/addons/ssi_warehouse_transfer/security/res_group_data.xml
odoo/addons/ssi_warehouse_transfer/static/description/icon.png
odoo/addons/ssi_warehouse_transfer/views/warehouse_transfer_type_views.xml
odoo/addons/ssi_warehouse_transfer/views/warehouse_transfer_views.xml
odoo14_addon_ssi_warehouse_transfer-14.0.2.3.0.dist-info/METADATA
odoo14_addon_ssi_warehouse_transfer-14.0.2.3.0.dist-info/WHEEL
odoo14_addon_ssi_warehouse_transfer-14.0.2.3.0.dist-info/top_level.txt
odoo14_addon_ssi_warehouse_transfer-14.0.2.3.0.dist-info/RECORD
