Metadata-Version: 2.1
Name: odoo14-addon-ssi_warehouse_transfer
Version: 14.0.2.3.0
Summary: Warehouse Transfer
Home-page: https://simetri-sinergi.id
Author: PT. Simetri Sinergi Indonesia, OpenSynergy Indonesia
License: AGPL-3
Classifier: Programming Language :: Python
Classifier: Framework :: Odoo
Classifier: Framework :: Odoo :: 14.0
Classifier: License :: OSI Approved :: GNU Affero General Public License v3
Requires-Python: >=3.6
Requires-Dist: odoo14-addon-ssi-m2o-configurator-mixin
Requires-Dist: odoo14-addon-ssi-master-data-mixin
Requires-Dist: odoo14-addon-ssi-product
Requires-Dist: odoo14-addon-ssi-product-line-mixin
Requires-Dist: odoo14-addon-ssi-stock
Requires-Dist: odoo14-addon-ssi-stock-location-m2o-configurator-mixin
Requires-Dist: odoo14-addon-ssi-stock-route-m2o-configurator-mixin
Requires-Dist: odoo14-addon-ssi-stock-warehouse-m2o-configurator-mixin
Requires-Dist: odoo14-addon-ssi-transaction-cancel-mixin
Requires-Dist: odoo14-addon-ssi-transaction-confirm-mixin
Requires-Dist: odoo14-addon-ssi-transaction-done-mixin
Requires-Dist: odoo14-addon-ssi-transaction-open-mixin
Requires-Dist: odoo14-addon-ssi-transaction-terminate-mixin
Requires-Dist: odoo<14.1dev,>=14.0a
